scikgraph/Agglomerative_clusters.py
scikgraph/Analyses.py
scikgraph/OClustR.py
scikgraph/SciKGraph.py
scikgraph/__init__.py
scikgraph/babelfy.py
scikgraph/bla.py
scikgraph/saveFiles/clusters1.txt
scikgraph/saveFiles/clusters2.txt
scikgraph/saveFiles/lastSession.sckg
scikgraph/static/Agglomerative_clusters.py
scikgraph/static/Analyses.py
scikgraph/static/OClustR.py
scikgraph/static/SciKGraph.py
scikgraph/static/custom.js
scikgraph/static/index.html
scikgraph/static/logo.png
scikgraph/static/main.css
scikgraph/static/main.js
scikgraph/static/myscripts.js
scikgraph/static/networks.js
scikgraph/static/onmi
scikgraph/static/sciKGraph.cx
scikgraph/static/style.css
scikgraph/static/styles.js
scikgraph/static/vendor.js
scikgraph/static/bla/Agglomerative_clusters.py
scikgraph/static/bla/Analyses.py
scikgraph/static/bla/OClustR.py
scikgraph/static/bla/SciKGraph.py
scikgraph/static/bla/custom.js
scikgraph/static/bla/index.html
scikgraph/static/bla/logo.png
scikgraph/static/bla/main.css
scikgraph/static/bla/main.js
scikgraph/static/bla/myscripts.js
scikgraph/static/bla/networks.js
scikgraph/static/bla/onmi
scikgraph/static/bla/sciKGraph.cx
scikgraph/static/bla/style.css
scikgraph/static/bla/styles (copy).js
scikgraph/static/bla/styles.js
scikgraph/static/bla/vendor.js
scikgraph/static/bla/temp/1d327552.scripts.js
scikgraph/static/bla/temp/3e4be17b.app.js
scikgraph/static/bla/temp/65d77273.vendor.js
scikgraph/static/bla/temp/networks.js
scikgraph/static/bla/temp/styles-create.js
scikgraph/static/bla/temp/styles.js
scikgraph/static/bla/temp/styles2.js
scikgraph/static/bla/temp/bla/styles.js
scikgraph/static/temp/1d327552.scripts.js
scikgraph/static/temp/3e4be17b.app.js
scikgraph/static/temp/65d77273.vendor.js
scikgraph/static/temp/networks.js
scikgraph/static/temp/styles-create.js
scikgraph/static/temp/styles.js
scikgraph/static/temp/styles2.js
scikgraph/templates/analyze.html
scikgraph/templates/createSciKGraph.html
scikgraph/templates/evolution.html
scikgraph-0.0.3.dist-info/METADATA
scikgraph-0.0.3.dist-info/WHEEL
scikgraph-0.0.3.dist-info/top_level.txt
scikgraph-0.0.3.dist-info/RECORD
